rvn-0.1.8.dist-info/METADATA
rvn-0.1.8.dist-info/WHEEL
rvn/__init__.py
rvn/rvn.cpython-310-x86_64-linux-gnu.so
rvn-0.1.8.dist-info/RECORD
