Metadata-Version: 2.4
Name: rvn
Version: 0.1.8
Requires-Dist: polars>=0.19
Summary: Lightning-fast LLM model introspection
Keywords: llm,gguf,diff,info
Home-Page: https://www.rvnllm.com/
Author: Ervin Bosenbacher <ervin.bosenbacher@rvnllm.com>
Author-email: Ervin Bosenbacher <ervin.bosenbacher@rvnllm.com>
License: MIT
Requires-Python: >=3.8
Project-URL: Source Code, https://github.com/rvnllm/rvnllm
